aisdk/VERSION.py
aisdk/__init__.py
aisdk/module1.py
aisdk-0.1.0.dist-info/LICENSE.txt
aisdk-0.1.0.dist-info/WHEEL
aisdk-0.1.0.dist-info/METADATA
aisdk-0.1.0.dist-info/RECORD
