Metadata-Version: 2.1
Name: aisdk
Version: 0.1.0
Summary: The description of the package
Home-page: https://github.com/python-poetry/poetry
License: MIT
Keywords: packaging,poetry
Author: Jose Luis Rosado
Author-email: jlrosado@ferrovial.com
Requires-Python: >=3.7,<4.0
Classifier: License :: OSI Approved :: MIT License
Classifier: Programming Language :: Python :: 3
Classifier: Programming Language :: Python :: 3.7
Classifier: Programming Language :: Python :: 3.8
Classifier: Programming Language :: Python :: 3.9
Requires-Dist: toml (>=0.10,<0.11)
Project-URL: Repository, https://github.com/python-poetry/poetry
